nfem/__init__.py
nfem/assembler.py
nfem/bracketing.py
nfem/canvas_3d.py
nfem/dof.py
nfem/element.py
nfem/html/model-viewer.html
nfem/html/solution-viewer.html
nfem/key_collection.py
nfem/model.py
nfem/model_status.py
nfem/node.py
nfem/plot.py
nfem/solve.py
nfem/spring.py
nfem/truss.py
nfem/viewer.py
nfem-4.1.8.dist-info/WHEEL
nfem-4.1.8.dist-info/METADATA
nfem-4.1.8.dist-info/RECORD
