Metadata-Version: 2.1
Name: nfem
Version: 4.1.8
Summary: NFEM Teaching Tool
Home-page: https://github.com/StatikTUM/nfem
License: MIT
Author: Thomas Oberbichler
Author-email: thomas.oberbichler@tum.de
Requires-Python: >=3.7,<4.0
Classifier: License :: OSI Approved :: MIT License
Classifier: Programming Language :: Python :: 3
Classifier: Programming Language :: Python :: 3.10
Classifier: Programming Language :: Python :: 3.7
Classifier: Programming Language :: Python :: 3.8
Classifier: Programming Language :: Python :: 3.9
Provides-Extra: qt
Requires-Dist: importlib-metadata (>=4.11,<5.0); python_version < "3.8"
Requires-Dist: notebook (>=5.3,<6.0); python_version < "3.8"
Requires-Dist: notebook (>=6.4,<7.0); python_version >= "3.8"
Requires-Dist: numpy (>=1.20,<2.0); python_version < "3.10"
Requires-Dist: numpy (>=1.22,<2.0); python_version >= "3.10"
Requires-Dist: plotly (>=5.5.0,<6.0.0)
Requires-Dist: scipy (>=1.4,<2.0); python_version < "3.10"
Requires-Dist: scipy (>=1.7.2,<2.0.0); python_version >= "3.10" and python_version < "3.11"
Requires-Dist: typing-extensions
Project-URL: Repository, https://github.com/StatikTUM/nfem
